pylars/__init__.py
pylars/analysis/__init__.py
pylars/analysis/breakdown.py
pylars/analysis/darkcount.py
pylars/analysis/fingerplot.py
pylars/analysis/ledwindow.py
pylars/analysis/mucoin.py
pylars/plotting/__init__.py
pylars/plotting/plot_mucoin.py
pylars/plotting/plotanalysis.py
pylars/plotting/plotfixwindow.py
pylars/plotting/plotpeaks.py
pylars/plotting/plotprocessed.py
pylars/plotting/plotrundb.py
pylars/plotting/plotwaveforms.py
pylars/processing/__init__.py
pylars/processing/fixwindow.py
pylars/processing/fixwindowprocessor.py
pylars/processing/peakprocessor.py
pylars/processing/peaks.py
pylars/processing/pulses.py
pylars/processing/rawprocessor.py
pylars/processing/waveforms.py
pylars/utils/__init__.py
pylars/utils/common.py
pylars/utils/gsheets_db.py
pylars/utils/input.py
pylars/utils/output.py
pylars_sipm-0.3.0.data/scripts/pylars
pylars_sipm-0.3.0.data/scripts/pylars_gainevo
pylars_sipm-0.3.0.data/scripts/pylars_led
pylars_sipm-0.3.0.dist-info/LICENSE
pylars_sipm-0.3.0.dist-info/METADATA
pylars_sipm-0.3.0.dist-info/WHEEL
pylars_sipm-0.3.0.dist-info/top_level.txt
pylars_sipm-0.3.0.dist-info/RECORD
