Metadata-Version: 2.1
Name: pylars-sipm
Version: 0.3.0
Summary: A python-based simple processor for data acquired with XenoDAQ
Home-page: https://github.com/ricmperes/PyLArS
Author: Ricardo Peres
Author-email: rperes@physik.uzh.ch
License: none
Platform: UNKNOWN
License-File: LICENSE
Requires-Dist: numpy
Requires-Dist: pandas
Requires-Dist: numba
Requires-Dist: tqdm
Requires-Dist: pytest
Requires-Dist: matplotlib
